discussion_agents/__init__.py
discussion_agents/cog/__init__.py
discussion_agents/cog/agent/__init__.py
discussion_agents/cog/agent/base.py
discussion_agents/cog/agent/critic.py
discussion_agents/cog/agent/expel.py
discussion_agents/cog/agent/generative_agents.py
discussion_agents/cog/agent/react.py
discussion_agents/cog/agent/reflexion.py
discussion_agents/cog/agent/self_refine.py
discussion_agents/cog/eval/__init__.py
discussion_agents/cog/eval/reflexion.py
discussion_agents/cog/functional/__init__.py
discussion_agents/cog/functional/critic.py
discussion_agents/cog/functional/expel.py
discussion_agents/cog/functional/generative_agents.py
discussion_agents/cog/functional/react.py
discussion_agents/cog/functional/reflexion.py
discussion_agents/cog/functional/self_refine.py
discussion_agents/cog/modules/memory/__init__.py
discussion_agents/cog/modules/memory/base.py
discussion_agents/cog/modules/memory/expel.py
discussion_agents/cog/modules/memory/generative_agents.py
discussion_agents/cog/modules/memory/react.py
discussion_agents/cog/modules/memory/reflexion.py
discussion_agents/cog/modules/memory/self_refine.py
discussion_agents/cog/modules/plan/__init__.py
discussion_agents/cog/modules/plan/base.py
discussion_agents/cog/modules/plan/generative_agents.py
discussion_agents/cog/modules/reflect/__init__.py
discussion_agents/cog/modules/reflect/base.py
discussion_agents/cog/modules/reflect/generative_agents.py
discussion_agents/cog/modules/reflect/reflexion.py
discussion_agents/cog/modules/score/__init__.py
discussion_agents/cog/modules/score/base.py
discussion_agents/cog/modules/score/generative_agents.py
discussion_agents/cog/persona/__init__.py
discussion_agents/cog/persona/base.py
discussion_agents/cog/persona/generative_agents.py
discussion_agents/cog/prompts/__init__.py
discussion_agents/cog/prompts/critic.py
discussion_agents/cog/prompts/expel.py
discussion_agents/cog/prompts/react.py
discussion_agents/cog/prompts/reflexion.py
discussion_agents-0.0.1.dist-info/LICENSE
discussion_agents-0.0.1.dist-info/METADATA
discussion_agents-0.0.1.dist-info/WHEEL
discussion_agents-0.0.1.dist-info/RECORD
