Metadata-Version: 2.1
Name: discussion_agents
Version: 0.0.1
Summary: A flexible agent library.
Home-page: https://github.com/alckasoc/discussion-agents
License: MIT
Keywords: packaging,poetry,agent,LLM
Author: Vincent Tu
Author-email: tuvincent0106@gmail.com
Requires-Python: >=3.9,<4.0
Classifier: License :: OSI Approved :: MIT License
Classifier: Programming Language :: Python :: 3
Classifier: Programming Language :: Python :: 3.9
Classifier: Programming Language :: Python :: 3.10
Classifier: Programming Language :: Python :: 3.11
Classifier: Topic :: Scientific/Engineering :: Artificial Intelligence
Requires-Dist: chardet (>=5.2.0,<6.0.0)
Requires-Dist: faiss-cpu (>=1.7.4,<2.0.0)
Requires-Dist: google-api-python-client (>=2.100.0)
Requires-Dist: langchain (>=0.0.354,<0.0.355)
Requires-Dist: langchain-core (>=0.1.5,<0.2.0)
Requires-Dist: langchainhub (>=0.1.14,<0.2.0)
Requires-Dist: numpy (>=1.25.2,<2.0.0)
Requires-Dist: openai (>=0.28.0,<0.29.0)
Requires-Dist: pandas (==1.5.3)
Requires-Dist: sentence-transformers (>=2.2.2,<3.0.0)
Requires-Dist: tiktoken (>=0.5.1,<0.6.0)
Requires-Dist: torch (>=2.0.0,!=2.0.1,!=2.1.0)
Requires-Dist: wikipedia (>=1.4.0,<2.0.0)
Project-URL: Repository, https://github.com/alckasoc/discussion-agents
